caustic/grammar/canonical/block.pg
caustic/grammar/canonical/canonical.pg
caustic/grammar/canonical/canonical.pgt
caustic/grammar/canonical/procedure.pg
caustic/grammar/canonical/procedure_actions.py
caustic/grammar/canonical/types.pg
caustic/grammar/canonical/expressions/expressions.pg
caustic/grammar/canonical/expressions/identifier.pg
caustic/grammar/canonical/expressions/literals.pg
caustic/grammar/canonical/expressions/operators.pg
caustic/grammar/canonical/expressions/operators_actions.py
caustic/grammar/canonical/statements/declare.pg
caustic/grammar/canonical/statements/objects.pg
caustic/grammar/canonical/statements/objects_actions.py
caustic/grammar/canonical/statements/statements.pg
caustic.grammar-2.2.0.dist-info/LICENSE
caustic.grammar-2.2.0.dist-info/METADATA
caustic.grammar-2.2.0.dist-info/WHEEL
caustic.grammar-2.2.0.dist-info/top_level.txt
caustic.grammar-2.2.0.dist-info/RECORD
